README.md
setup.py
vbigbang_thread_logging/__init__.py
vbigbang_thread_logging/core.py
vbigbang_thread_logging.egg-info/PKG-INFO
vbigbang_thread_logging.egg-info/SOURCES.txt
vbigbang_thread_logging.egg-info/dependency_links.txt
vbigbang_thread_logging.egg-info/not-zip-safe
vbigbang_thread_logging.egg-info/top_level.txt